aibaba_ai/__init__.py
aibaba_ai/_api/__init__.py
aibaba_ai/_api/interactive_env.py
aibaba_ai/_api/module_import.py
aibaba_ai/_api/path.py
aibaba_ai/adapters/__init__.py
aibaba_ai/adapters/openai.py
aibaba_ai/agents/__init__.py
aibaba_ai/agents/agent.py
aibaba_ai/agents/agent_iterator.py
aibaba_ai/agents/agent_toolkits/__init__.py
aibaba_ai/agents/agent_toolkits/ainetwork/__init__.py
aibaba_ai/agents/agent_toolkits/ainetwork/toolkit.py
aibaba_ai/agents/agent_toolkits/amadeus/toolkit.py
aibaba_ai/agents/agent_toolkits/azure_cognitive_services.py
aibaba_ai/agents/agent_toolkits/base.py
aibaba_ai/agents/agent_toolkits/clickup/__init__.py
aibaba_ai/agents/agent_toolkits/clickup/toolkit.py
aibaba_ai/agents/agent_toolkits/conversational_retrieval/__init__.py
aibaba_ai/agents/agent_toolkits/conversational_retrieval/openai_functions.py
aibaba_ai/agents/agent_toolkits/conversational_retrieval/tool.py
aibaba_ai/agents/agent_toolkits/csv/__init__.py
aibaba_ai/agents/agent_toolkits/file_management/__init__.py
aibaba_ai/agents/agent_toolkits/file_management/toolkit.py
aibaba_ai/agents/agent_toolkits/github/__init__.py
aibaba_ai/agents/agent_toolkits/github/toolkit.py
aibaba_ai/agents/agent_toolkits/gitlab/__init__.py
aibaba_ai/agents/agent_toolkits/gitlab/toolkit.py
aibaba_ai/agents/agent_toolkits/gmail/__init__.py
aibaba_ai/agents/agent_toolkits/gmail/toolkit.py
aibaba_ai/agents/agent_toolkits/jira/__init__.py
aibaba_ai/agents/agent_toolkits/jira/toolkit.py
aibaba_ai/agents/agent_toolkits/json/__init__.py
aibaba_ai/agents/agent_toolkits/json/base.py
aibaba_ai/agents/agent_toolkits/json/prompt.py
aibaba_ai/agents/agent_toolkits/json/toolkit.py
aibaba_ai/agents/agent_toolkits/multion/__init__.py
aibaba_ai/agents/agent_toolkits/multion/toolkit.py
aibaba_ai/agents/agent_toolkits/nasa/__init__.py
aibaba_ai/agents/agent_toolkits/nasa/toolkit.py
aibaba_ai/agents/agent_toolkits/nla/__init__.py
aibaba_ai/agents/agent_toolkits/nla/tool.py
aibaba_ai/agents/agent_toolkits/nla/toolkit.py
aibaba_ai-0.3.33.dist-info/LICENSE
aibaba_ai-0.3.33.dist-info/METADATA
aibaba_ai-0.3.33.dist-info/WHEEL
aibaba_ai-0.3.33.dist-info/entry_points.txt
aibaba_ai-0.3.33.dist-info/RECORD
