Metadata-Version: 2.3
Name: aibaba_ai
Version: 0.3.33
Summary: Framework for building and deploying LLM-powered applications.
License: MIT
Requires-Python: >=3.9,<4.0
Classifier: License :: OSI Approved :: MIT License
Classifier: Programming Language :: Python :: 3
Classifier: Programming Language :: Python :: 3.9
Classifier: Programming Language :: Python :: 3.10
Classifier: Programming Language :: Python :: 3.11
Classifier: Programming Language :: Python :: 3.12
Classifier: Programming Language :: Python :: 3.13
Requires-Dist: PyYAML (>=5.3)
Requires-Dist: SQLAlchemy (>=1.4,<3)
Requires-Dist: aibaba_ai_core (>=0.3.31,<0.4.0)
Requires-Dist: aibaba_ai_text_splitters (>=0.3.6,<0.4.0)
Requires-Dist: aiohttp (>=3.8.3,<4.0.0)
Requires-Dist: async-timeout (>=4.0.0,<5.0.0) ; python_version < "3.11"
Requires-Dist: langsmith (>=0.1.17,<0.3)
Requires-Dist: numpy (>=1.22.4,<2) ; python_version < "3.12"
Requires-Dist: numpy (>=1.26.2,<3) ; python_version >= "3.12"
Requires-Dist: pydantic (>=2.7.4,<3.0.0)
Requires-Dist: requests (>=2,<3)
Requires-Dist: tenacity (>=8.1.0,!=8.4.0,<10)
Project-URL: Repository, https://github.com/aibaba-ai/aibaba-ai
Project-URL: Release Notes, https://github.com/aibaba-ai/aibaba-ai/releases?q=tag%3A%22aiagentsforce%3D%3D0%22&expanded=true
Project-URL: Source Code, https://github.com/aibaba-ai/aibaba-ai/tree/master/libs/aibaba-ai
